shotty/__init__.py
shotty/api.py
shotty/rest.py
shotty-0.1.6.dist-info/DESCRIPTION.rst
shotty-0.1.6.dist-info/METADATA
shotty-0.1.6.dist-info/RECORD
shotty-0.1.6.dist-info/WHEEL
shotty-0.1.6.dist-info/metadata.json
shotty-0.1.6.dist-info/top_level.txt
shotty-api/__init__.py
shotty-api/shotty.py
