Metadata-Version: 2.0
Name: shotty
Version: 0.1.6
Summary: UNKNOWN
Home-page: https://shottyapp.com
Author: Ilya Lindberg
Author-email: ilya.lindberg@gmail.com
License: UNKNOWN
Platform: UNKNOWN
Requires-Dist: socketIO-client
